{"data":[{"team_id":"6948","type":"injury","player_id":"4979","player_name":"Gorriaran, Fernando","related_player_id":null,"related_player_name":null,"minute":21,"extra_minute":null,"reason":null,"injuried":true,"own_goal":false,"penalty":false,"result":null},{"team_id":"6948","type":"back from injury","player_id":"4979","player_name":"Gorriaran, Fernando","related_player_id":null,"related_player_name":null,"minute":23,"extra_minute":null,"reason":null,"injuried":false,"own_goal":false,"penalty":false,"result":null},{"team_id":"6954","type":"substitution","player_id":"10736","player_name":"Maidana, Jonatan","related_player_id":"161882","related_player_name":"Medina, Alan","minute":36,"extra_minute":null,"reason":null,"injuried":null,"own_goal":false,"penalty":false,"result":null},{"team_id":"6948","type":"goal","player_id":"4970","player_name":"Sandoval, Walter","related_player_id":null,"related_player_name":null,"minute":40,"extra_minute":null,"reason":null,"injuried":null,"own_goal":false,"penalty":false,"result":"0-1"},{"team_id":"6954","type":"yellowcard","player_id":"148","player_name":"Mora, Adrian","related_player_id":null,"related_player_name":null,"minute":45,"extra_minute":1,"reason":null,"injuried":null,"own_goal":false,"penalty":false,"result":null},{"team_id":"6948","type":"goal","player_id":"4987","player_name":"Rivero, Octavio","related_player_id":null,"related_player_name":null,"minute":53,"extra_minute":null,"reason":null,"injuried":null,"own_goal":false,"penalty":false,"result":"0-2"},{"team_id":"6954","type":"substitution","player_id":"6149","player_name":"Abella, Diego","related_player_id":"6129","related_player_name":"Estrada, Michael","minute":56,"extra_minute":null,"reason":null,"injuried":null,"own_goal":false,"penalty":false,"result":null},{"team_id":"6954","type":"substitution","player_id":"151","player_name":"Guemez, Javier","related_player_id":"149","related_player_name":"Castaneda, Kevin","minute":56,"extra_minute":null,"reason":null,"injuried":null,"own_goal":false,"penalty":false,"result":null},{"team_id":"6948","type":"substitution","player_id":"14343","player_name":"Garnica, Bryan","related_player_id":"4978","related_player_name":"Rivas, Ulises","minute":68,"extra_minute":null,"reason":null,"injuried":null,"own_goal":false,"penalty":false,"result":null},{"team_id":"6954","type":"yellowcard","player_id":"106","player_name":"Sambueza, Rubens","related_player_id":null,"related_player_name":null,"minute":69,"extra_minute":null,"reason":null,"injuried":null,"own_goal":false,"penalty":false,"result":null},{"team_id":"6948","type":"injury","player_id":"161817","player_name":"Andrade, David","related_player_id":null,"related_player_name":null,"minute":69,"extra_minute":null,"reason":null,"injuried":true,"own_goal":false,"penalty":false,"result":null},{"team_id":"6948","type":"back from injury","player_id":"161817","player_name":"Andrade, David","related_player_id":null,"related_player_name":null,"minute":71,"extra_minute":null,"reason":null,"injuried":false,"own_goal":false,"penalty":false,"result":null},{"team_id":"6948","type":"substitution","player_id":"4987","player_name":"Rivero, Octavio","related_player_id":"4980","related_player_name":"Aguirre, Eduardo","minute":78,"extra_minute":null,"reason":null,"injuried":null,"own_goal":false,"penalty":false,"result":null},{"team_id":"6948","type":"substitution","player_id":"4970","player_name":"Sandoval, Walter","related_player_id":"4984","related_player_name":"Lozano, Adrian","minute":79,"extra_minute":null,"reason":null,"injuried":null,"own_goal":false,"penalty":false,"result":null},{"team_id":"6954","type":"substitution","player_id":"22484","player_name":"Cisneros, Carlos","related_player_id":"254228","related_player_name":"Plata, Joao","minute":81,"extra_minute":null,"reason":null,"injuried":null,"own_goal":false,"penalty":false,"result":null},{"team_id":"6948","type":"substitution","player_id":"4985","player_name":"Valdes, Diego","related_player_id":"4988","related_player_name":"Cervantes, Alan","minute":87,"extra_minute":null,"reason":null,"injuried":null,"own_goal":false,"penalty":false,"result":null},{"team_id":"6948","type":"substitution","player_id":"4981","player_name":"Furch, Julio","related_player_id":"181313","related_player_name":"Ocejo, Jesus","minute":87,"extra_minute":null,"reason":null,"injuried":null,"own_goal":false,"penalty":false,"result":null},{"team_id":"6954","type":"yellowcard","player_id":"254216","player_name":"Sartiaguin, Brandon","related_player_id":null,"related_player_name":null,"minute":89,"extra_minute":null,"reason":null,"injuried":null,"own_goal":false,"penalty":false,"result":null},{"team_id":"6954","type":"goal","player_id":"6129","player_name":"Estrada, Michael","related_player_id":null,"related_player_name":null,"minute":90,"extra_minute":3,"reason":null,"injuried":null,"own_goal":false,"penalty":false,"result":"1-2"}],"meta":{"requests_left":2858,"user":"kenpetere","plan":"pack_20","pages":1,"page":1,"count":19,"total":19,"msg":null}}