{"data":{"home":{"formation":"4-4-2","confirmed_formation":1,"squad":[{"player":{"id":"110928","name":null,"common_name":"Kim, Young-Kwang","firstname":"Young-Kwang","lastname":"Kim","weight":null,"height":null,"img":"https://cdn.soccersapi.com/images/soccer/players/50/110928.png","country":{"id":null,"name":null,"cc":null}},"number":"41","captain":null,"position":"G","order":1},{"player":{"id":"99016","name":null,"common_name":"Tae-heui, Lee","firstname":"Lee","lastname":"Tae-heui","weight":null,"height":null,"img":"https://cdn.soccersapi.com/images/soccer/players/50/99016.png","country":{"id":null,"name":null,"cc":null}},"number":"32","captain":null,"position":"D","order":2},{"player":{"id":"99009","name":null,"common_name":"Jovanovic, Igor","firstname":"Igor","lastname":"Jovanovic","weight":null,"height":null,"img":"https://cdn.soccersapi.com/images/soccer/players/50/99009.png","country":{"id":null,"name":null,"cc":null}},"number":"2","captain":null,"position":"D","order":3},{"player":{"id":"99029","name":null,"common_name":"Je-un, Yeon","firstname":"Yeon","lastname":"Je-un","weight":null,"height":null,"img":"https://cdn.soccersapi.com/images/soccer/players/50/99029.png","country":{"id":null,"name":null,"cc":null}},"number":"20","captain":null,"position":"D","order":4},{"player":{"id":"250898","name":null,"common_name":"Ji-moog, Choi","firstname":"Choi","lastname":"Ji-moog","weight":null,"height":null,"img":"https://cdn.soccersapi.com/images/soccer/players/50/250898.png","country":{"id":null,"name":null,"cc":null}},"number":"34","captain":null,"position":"D","order":5},{"player":{"id":"51892","name":null,"common_name":"Jamshid Iskanderov","firstname":"","lastname":"Jamshid Iskanderov","weight":null,"height":null,"img":"https://cdn.soccersapi.com/images/soccer/players/50/51892.png","country":{"id":null,"name":null,"cc":null}},"number":"16","captain":null,"position":"M","order":6},{"player":{"id":"99017","name":null,"common_name":"Dong-hyeon, Kim","firstname":"Kim","lastname":"Dong-hyeon","weight":null,"height":null,"img":"https://cdn.soccersapi.com/images/soccer/players/50/99017.png","country":{"id":null,"name":null,"cc":null}},"number":"14","captain":null,"position":"M","order":7},{"player":{"id":"99012","name":null,"common_name":"Jae-Won, Lee","firstname":"Lee","lastname":"Jae-Won","weight":null,"height":null,"img":"https://cdn.soccersapi.com/images/soccer/players/50/99012.png","country":{"id":null,"name":null,"cc":null}},"number":"19","captain":null,"position":"F","order":8},{"player":{"id":"99031","name":null,"common_name":"Su-il, Park","firstname":"Park","lastname":"Su-il","weight":null,"height":null,"img":"https://cdn.soccersapi.com/images/soccer/players/50/99031.png","country":{"id":null,"name":null,"cc":null}},"number":"3","captain":null,"position":"M","order":9},{"player":{"id":"99033","name":null,"common_name":"Oh-baek, Choi","firstname":"Choi","lastname":"Oh-baek","weight":null,"height":null,"img":"https://cdn.soccersapi.com/images/soccer/players/50/99033.png","country":{"id":null,"name":null,"cc":null}},"number":"17","captain":null,"position":"M","order":10},{"player":{"id":"99023","name":null,"common_name":"Seon-yeong, Lim","firstname":"Lim","lastname":"Seon-yeong","weight":null,"height":null,"img":"https://cdn.soccersapi.com/images/soccer/players/50/99023.png","country":{"id":null,"name":null,"cc":null}},"number":"5","captain":null,"position":"M","order":11}]},"away":{"formation":"3-5-2","confirmed_formation":1,"squad":[{"player":{"id":"99060","name":null,"common_name":"Dong Geon, No","firstname":"No","lastname":"Dong Geon","weight":null,"height":null,"img":"https://cdn.soccersapi.com/images/soccer/players/50/99060.png","country":{"id":null,"name":null,"cc":null}},"number":"19","captain":null,"position":"G","order":1},{"player":{"id":"8111","name":null,"common_name":"Henry, Doneil","firstname":"Doneil Jor-Dee Ashley","lastname":"Henry","weight":"82","height":"188","img":"https://cdn.soccersapi.com/images/soccer/players/50/8111.png","country":{"id":"28","name":"Canada","cc":"ca"}},"number":"4","captain":null,"position":"D","order":2},{"player":{"id":"8099","name":null,"common_name":"Sang-gi, Min","firstname":"Sang-gi","lastname":"Min","weight":"79","height":"184","img":"https://cdn.soccersapi.com/images/soccer/players/50/8099.png","country":{"id":"98","name":"Republic of Korea","cc":"kr"}},"number":"39","captain":null,"position":"D","order":3},{"player":{"id":"99065","name":null,"common_name":"Sang-Min, Yang","firstname":"Yang","lastname":"Sang-Min","weight":null,"height":null,"img":"https://cdn.soccersapi.com/images/soccer/players/50/99065.png","country":{"id":null,"name":null,"cc":null}},"number":"3","captain":null,"position":"D","order":4},{"player":{"id":"99087","name":null,"common_name":"Ku, Dae yeong","firstname":"Dae yeong","lastname":"Ku","weight":null,"height":null,"img":"https://cdn.soccersapi.com/images/soccer/players/50/99087.png","country":{"id":null,"name":null,"cc":null}},"number":"90","captain":null,"position":"D","order":5},{"player":{"id":"99063","name":null,"common_name":"Sanghyeok, Park","firstname":"Park","lastname":"Sanghyeok","weight":null,"height":null,"img":"https://cdn.soccersapi.com/images/soccer/players/50/99063.png","country":{"id":null,"name":null,"cc":null}},"number":"98","captain":null,"position":"F","order":6},{"player":{"id":"99070","name":null,"common_name":"Seung-Beom, Ko","firstname":"Ko","lastname":"Seung-Beom","weight":null,"height":null,"img":"https://cdn.soccersapi.com/images/soccer/players/50/99070.png","country":{"id":null,"name":null,"cc":null}},"number":"77","captain":null,"position":"M","order":7},{"player":{"id":"99058","name":null,"common_name":"Ki Hun, Yeom","firstname":"Yeom","lastname":"Ki Hun","weight":null,"height":null,"img":"https://cdn.soccersapi.com/images/soccer/players/50/99058.png","country":{"id":null,"name":null,"cc":null}},"number":"26","captain":null,"position":"M","order":8},{"player":{"id":"8112","name":null,"common_name":"Min-woo, Kim","firstname":"Min-woo","lastname":"Kim","weight":"69","height":"172","img":"https://cdn.soccersapi.com/images/soccer/players/50/8112.png","country":{"id":"98","name":"Republic of Korea","cc":"kr"}},"number":"10","captain":null,"position":"M","order":9},{"player":{"id":"20021","name":null,"common_name":"Krpic, Sulejman","firstname":"Sulejman","lastname":"Krpic","weight":"90","height":"187","img":"https://cdn.soccersapi.com/images/soccer/players/50/20021.png","country":{"id":"23","name":"Bosnia & Herzegovina","cc":"ba"}},"number":"7","captain":null,"position":"F","order":10},{"player":{"id":"26809","name":null,"common_name":"Taggart, Adam","firstname":"Adam","lastname":"Taggart","weight":null,"height":null,"img":"https://cdn.soccersapi.com/images/soccer/players/50/26809.png","country":{"id":null,"name":null,"cc":null}},"number":"18","captain":null,"position":"F","order":11}]}},"meta":{"requests_left":1482,"user":"kenpetere","plan":"pack_20","pages":1,"page":1,"count":1,"total":1,"msg":null}}