{"data":[{"team_id":"1051","type":"goal","player_id":"1296","player_name":"Vieira, Douglas","related_player_id":552638,"related_player_name":"Pereira, Leandro","minute":20,"extra_minute":null,"reason":null,"injuried":null,"own_goal":false,"penalty":false,"result":"1-0"},{"team_id":"1051","type":"goal","player_id":"1304","player_name":"Pereira, Leandro","related_player_id":122685,"related_player_name":"Vieira, Douglas","minute":25,"extra_minute":null,"reason":null,"injuried":null,"own_goal":false,"penalty":false,"result":"2-0"},{"team_id":"1053","type":"yellowcard","player_id":"1320","player_name":"Hirose, Rikuto","related_player_id":null,"related_player_name":null,"minute":31,"extra_minute":null,"reason":null,"injuried":null,"own_goal":false,"penalty":false,"result":null},{"team_id":"1053","type":"substitution","player_id":"1320","player_name":"Hirose, Rikuto","related_player_id":"1327","related_player_name":"Ueda, Ayase","minute":46,"extra_minute":null,"reason":null,"injuried":null,"own_goal":false,"penalty":false,"result":null},{"team_id":"1053","type":"substitution","player_id":"1316","player_name":"Doi, Shoma","related_player_id":"1328","related_player_name":"Araki, Ryotaro","minute":60,"extra_minute":null,"reason":null,"injuried":null,"own_goal":false,"penalty":false,"result":null},{"team_id":"1051","type":"substitution","player_id":"1297","player_name":"Kashiwa, Yoshifumi","related_player_id":"1310","related_player_name":"Asano, Yuya","minute":66,"extra_minute":null,"reason":null,"injuried":null,"own_goal":false,"penalty":false,"result":null},{"team_id":"1053","type":"substitution","player_id":"1322","player_name":"Silva, Leo","related_player_id":"1326","related_player_name":"Nago, Shintaro","minute":66,"extra_minute":null,"reason":null,"injuried":null,"own_goal":false,"penalty":false,"result":null},{"team_id":"1051","type":"injury","player_id":"1296","player_name":"Vieira, Douglas","related_player_id":null,"related_player_name":null,"minute":76,"extra_minute":null,"reason":null,"injuried":true,"own_goal":false,"penalty":false,"result":null},{"team_id":"1051","type":"substitution","player_id":"1296","player_name":"Vieira, Douglas","related_player_id":"1309","related_player_name":"Higashi, Shunki","minute":77,"extra_minute":null,"reason":null,"injuried":null,"own_goal":false,"penalty":false,"result":null},{"team_id":"1053","type":"yellowcard","player_id":"1317","player_name":"Sekigawa, Ikuma","related_player_id":null,"related_player_name":null,"minute":77,"extra_minute":null,"reason":null,"injuried":null,"own_goal":false,"penalty":false,"result":null},{"team_id":"1053","type":"yellowcard","player_id":"1321","player_name":"Machida, Koki","related_player_id":null,"related_player_name":null,"minute":84,"extra_minute":null,"reason":null,"injuried":null,"own_goal":false,"penalty":false,"result":null},{"team_id":"1051","type":"goal","player_id":"1305","player_name":"Morishima, Tsukasa","related_player_id":552638,"related_player_name":"Pereira, Leandro","minute":84,"extra_minute":null,"reason":null,"injuried":null,"own_goal":false,"penalty":false,"result":"3-0"},{"team_id":"1051","type":"substitution","player_id":"1301","player_name":"Aoyama, Toshihiro","related_player_id":"1308","related_player_name":"Matsumoto, Hiroya","minute":86,"extra_minute":null,"reason":null,"injuried":null,"own_goal":false,"penalty":false,"result":null}],"meta":{"requests_left":2467,"user":"kenpetere","plan":"pack_20","pages":1,"page":1,"count":13,"total":13,"msg":null}}