{"data":[{"team_id":"1038","type":"goal","player_id":"15019","player_name":"Esaka, Ataru","related_player_id":null,"related_player_name":null,"minute":13,"extra_minute":null,"reason":null,"injuried":null,"own_goal":false,"penalty":false,"result":"1-0"},{"team_id":"1038","type":"yellowcard","player_id":"15017","player_name":"Takahashi, Shunki","related_player_id":null,"related_player_name":null,"minute":16,"extra_minute":null,"reason":null,"injuried":null,"own_goal":false,"penalty":false,"result":null},{"team_id":"1038","type":"goal","player_id":"15020","player_name":"Olunga, Michael","related_player_id":null,"related_player_name":null,"minute":20,"extra_minute":null,"reason":null,"injuried":null,"own_goal":false,"penalty":false,"result":"2-0"},{"team_id":"1038","type":"injury","player_id":"15021","player_name":"Segawa, Yusuke","related_player_id":null,"related_player_name":null,"minute":28,"extra_minute":null,"reason":null,"injuried":true,"own_goal":false,"penalty":false,"result":null},{"team_id":"1038","type":"injury","player_id":"15011","player_name":"Kim, Seung Gyu","related_player_id":null,"related_player_name":null,"minute":29,"extra_minute":null,"reason":null,"injuried":true,"own_goal":false,"penalty":false,"result":null},{"team_id":"1038","type":"back from injury","player_id":"15011","player_name":"Kim, Seung Gyu","related_player_id":null,"related_player_name":null,"minute":30,"extra_minute":null,"reason":null,"injuried":false,"own_goal":false,"penalty":false,"result":null},{"team_id":"1038","type":"substitution","player_id":"15021","player_name":"Segawa, Yusuke","related_player_id":"212","related_player_name":"Kamiya, Yuta","minute":30,"extra_minute":null,"reason":null,"injuried":null,"own_goal":false,"penalty":false,"result":null},{"team_id":"1038","type":"substitution","player_id":"15018","player_name":"Someya, Yuta","related_player_id":"15024","related_player_name":"Takahashi, Yuji","minute":46,"extra_minute":null,"reason":null,"injuried":null,"own_goal":false,"penalty":false,"result":null},{"team_id":"1049","type":"substitution","player_id":"10792","player_name":"Shirai, Kosuke","related_player_id":"10802","related_player_name":"Fernandes, Lucas","minute":57,"extra_minute":null,"reason":null,"injuried":null,"own_goal":false,"penalty":false,"result":null},{"team_id":"1038","type":"goal","player_id":"15019","player_name":"Esaka, Ataru","related_player_id":215954,"related_player_name":"Cristiano","minute":58,"extra_minute":null,"reason":null,"injuried":null,"own_goal":false,"penalty":false,"result":"3-0"},{"team_id":"1038","type":"goal","player_id":"15020","player_name":"Olunga, Michael","related_player_id":null,"related_player_name":null,"minute":65,"extra_minute":null,"reason":null,"injuried":null,"own_goal":false,"penalty":false,"result":"4-0"},{"team_id":"1049","type":"goal","player_id":"10789","player_name":"Arano, Takuma","related_player_id":null,"related_player_name":null,"minute":68,"extra_minute":null,"reason":null,"injuried":null,"own_goal":false,"penalty":false,"result":"4-1"},{"team_id":"1049","type":"substitution","player_id":"10786","player_name":"Bothroyd, Jay","related_player_id":"10801","related_player_name":"Lopes, Anderson","minute":72,"extra_minute":null,"reason":null,"injuried":null,"own_goal":false,"penalty":false,"result":null},{"team_id":"1049","type":"goal","player_id":"10788","player_name":"Suzuki, Musashi","related_player_id":null,"related_player_name":null,"minute":76,"extra_minute":null,"reason":null,"injuried":null,"own_goal":false,"penalty":false,"result":"4-2"},{"team_id":"1049","type":"substitution","player_id":"10794","player_name":"Min-Tae, Kim","related_player_id":"10797","related_player_name":"Komai, Yoshiaki","minute":79,"extra_minute":null,"reason":null,"injuried":null,"own_goal":false,"penalty":false,"result":null},{"team_id":"1038","type":"substitution","player_id":"15011","player_name":"Kim, Seung Gyu","related_player_id":"15022","related_player_name":"Takimoto, Haruhiko","minute":81,"extra_minute":null,"reason":null,"injuried":null,"own_goal":false,"penalty":false,"result":null}],"meta":{"requests_left":2472,"user":"kenpetere","plan":"pack_20","pages":1,"page":1,"count":16,"total":16,"msg":null}}