{"data":[{"important":0,"order":1,"goal":0,"minute":1,"extra_minute":0,"comment":"Christof Dierick starts the match. Oud-Heverlee with the kick-off in Ostend."},{"important":1,"order":2,"goal":0,"minute":2,"extra_minute":0,"comment":"Arthur Theate (Oostende) has received a yellow card from Christof Dierick."},{"important":1,"order":3,"goal":0,"minute":11,"extra_minute":0,"comment":"In the minute 11, At Versluys Arena, Toon Raemaekers has been yellow-carded for the away team."},{"important":1,"order":4,"goal":1,"minute":26,"extra_minute":0,"comment":"Goal! Fashion Sakala gives Oostende a 1-0 lead."},{"important":1,"order":5,"goal":0,"minute":33,"extra_minute":0,"comment":"Oostende's Makhtar Gueye has been booked in Ostend."},{"important":1,"order":6,"goal":0,"minute":36,"extra_minute":0,"comment":"In the minute 36, The home team have replaced Robbie D'Haese with Theo Ndicka. This is the first substitution made today by Alexander Blessin."},{"important":1,"order":7,"goal":0,"minute":41,"extra_minute":0,"comment":"Fashion Sakala (Oostende) has received a first yellow card."},{"important":1,"order":8,"goal":0,"minute":45,"extra_minute":1,"comment":"Thibault Vlietinck (Oud-Heverlee) gets a yellow card."},{"important":1,"order":9,"goal":0,"minute":72,"extra_minute":0,"comment":"In the minute 72, Marc Brys (Oud-Heverlee) is making a first substitution, with Milan Tucic replacing Thibault Vlietinck."},{"important":1,"order":10,"goal":1,"minute":79,"extra_minute":0,"comment":"Goal! Oud-Heverlee reduce the deficit to 3-1 through Mathieu Maertens."},{"important":0,"order":11,"goal":0,"minute":90,"extra_minute":null,"comment":"That's full-time at Versluys Arena. The final score is 3-1."}],"meta":{"requests_left":2801,"user":"19220464","plan":"pack_20","pages":1,"page":1,"count":11,"total":11,"msg":null}}