{"data":[{"important":0,"order":1,"goal":0,"minute":1,"extra_minute":0,"comment":"The referee blows his whistle to start the first-half. Stoke with the kick-off."},{"important":1,"order":2,"goal":0,"minute":34,"extra_minute":0,"comment":"Ben Thompson for Millwall has been booked by Jeremy Simpson and receives a first yellow card."},{"important":0,"order":3,"goal":0,"minute":45,"extra_minute":null,"comment":"In the minute 45, The first-half is over."},{"important":0,"order":4,"goal":0,"minute":46,"extra_minute":0,"comment":"It's Millwall with the kick-off after the break."},{"important":1,"order":5,"goal":0,"minute":64,"extra_minute":0,"comment":"The home team have replaced Jon Dadi Bödvarsson with Matt Smith. This is the first substitution made today by Gary Rowett."},{"important":1,"order":6,"goal":0,"minute":64,"extra_minute":0,"comment":"In the minute 64, Connor Mahoney is on a sub for Mason Bennett for Millwall."},{"important":1,"order":7,"goal":0,"minute":64,"extra_minute":0,"comment":"Michael O'Neill is making the team's first substitution at The Den with Steven Fletcher replacing Tyrese Campbell."},{"important":1,"order":8,"goal":0,"minute":76,"extra_minute":0,"comment":"Michael O'Neill (Stoke) is making a second substitution, with Jacob Brown replacing Sam Vokes."},{"important":1,"order":9,"goal":0,"minute":82,"extra_minute":0,"comment":"In the minute 82, Murray Wallace is replacing Scott Malone for Millwall at The Den."},{"important":1,"order":10,"goal":0,"minute":85,"extra_minute":0,"comment":"Stoke make their third substitution with Jordan Thompson replacing Nick Powell."},{"important":0,"order":12,"goal":0,"minute":90,"extra_minute":null,"comment":"That's full-time at The Den. The final score is 0-0."},{"important":1,"order":11,"goal":0,"minute":90,"extra_minute":0,"comment":"Jacob Brown (Stoke) has received a yellow card from Jeremy Simpson."}],"meta":{"requests_left":530,"user":"19220464","plan":"pack_20","pages":1,"page":1,"count":12,"total":12,"msg":null}}