{"data":[{"team_id":"3937","type":"goal","player_id":"4411","player_name":"Vinas, Federico","related_player_id":158395,"related_player_name":"Ibarra, Renato","minute":5,"extra_minute":null,"reason":null,"injuried":null,"own_goal":false,"penalty":false,"result":"1-0"},{"team_id":"3937","type":"yellowcard","player_id":"18125","player_name":"Rodriguez, Guido","related_player_id":null,"related_player_name":null,"minute":20,"extra_minute":null,"reason":null,"injuried":null,"own_goal":false,"penalty":false,"result":null},{"team_id":"3937","type":"substitution","player_id":"45438","player_name":"Ibarra Mina, Alex","related_player_id":"102967","related_player_name":"Benedetti, Nicolas","minute":28,"extra_minute":null,"reason":null,"injuried":null,"own_goal":false,"penalty":false,"result":null},{"team_id":"3363","type":"yellowcard","player_id":"14168","player_name":"Pizarro, Rodolfo","related_player_id":null,"related_player_name":null,"minute":29,"extra_minute":null,"reason":null,"injuried":null,"own_goal":false,"penalty":false,"result":null},{"team_id":"3937","type":"goal","player_id":"4408","player_name":"Sanchez, Richard","related_player_id":755408,"related_player_name":"Martin, Henry","minute":41,"extra_minute":null,"reason":null,"injuried":null,"own_goal":false,"penalty":false,"result":"2-0"},{"team_id":"3363","type":"substitution","player_id":"14168","player_name":"Pizarro, Rodolfo","related_player_id":"4402","related_player_name":"Janssen, Vincent","minute":46,"extra_minute":null,"reason":null,"injuried":null,"own_goal":false,"penalty":false,"result":null},{"team_id":"3937","type":"yellowcard","player_id":"102967","player_name":"Benedetti, Nicolas","related_player_id":null,"related_player_name":null,"minute":55,"extra_minute":null,"reason":null,"injuried":null,"own_goal":false,"penalty":false,"result":null},{"team_id":"3363","type":"substitution","player_id":"4389","player_name":"Layun, Miguel","related_player_id":"4387","related_player_name":"Montes, Cesar","minute":57,"extra_minute":null,"reason":null,"injuried":null,"own_goal":false,"penalty":false,"result":null},{"team_id":"3937","type":"substitution","player_id":"4408","player_name":"Sanchez, Richard","related_player_id":"4407","related_player_name":"Gonzalez, Ruben","minute":67,"extra_minute":null,"reason":null,"injuried":null,"own_goal":false,"penalty":false,"result":null},{"team_id":"3363","type":"substitution","player_id":"4393","player_name":"Gallardo, Jesus","related_player_id":"21557","related_player_name":"Meza, Maximiliano","minute":70,"extra_minute":null,"reason":null,"injuried":null,"own_goal":false,"penalty":false,"result":null},{"team_id":"3937","type":"injury","player_id":"4404","player_name":"Aguilar, Paul","related_player_id":null,"related_player_name":null,"minute":72,"extra_minute":null,"reason":null,"injuried":true,"own_goal":false,"penalty":false,"result":null},{"team_id":"3937","type":"back from injury","player_id":"4404","player_name":"Aguilar, Paul","related_player_id":null,"related_player_name":null,"minute":73,"extra_minute":null,"reason":null,"injuried":false,"own_goal":false,"penalty":false,"result":null},{"team_id":"3363","type":"goal","player_id":"4394","player_name":"Funes Mori, Rogelio","related_player_id":186847,"related_player_name":"Pabon, Dorlan","minute":75,"extra_minute":null,"reason":null,"injuried":null,"own_goal":false,"penalty":false,"result":"2-1"},{"team_id":"3363","type":"yellowcard","player_id":"4386","player_name":"Medina, Stefan","related_player_id":null,"related_player_name":null,"minute":79,"extra_minute":null,"reason":null,"injuried":null,"own_goal":false,"penalty":false,"result":null},{"team_id":"3937","type":"substitution","player_id":"13082","player_name":"Martinez, Roger","related_player_id":"4412","related_player_name":"Dos Santos, Giovani","minute":88,"extra_minute":null,"reason":null,"injuried":null,"own_goal":false,"penalty":false,"result":null},{"team_id":"3363","type":"yellowcard","player_id":"22420","player_name":"Vangioni, Leonel","related_player_id":null,"related_player_name":null,"minute":89,"extra_minute":null,"reason":null,"injuried":null,"own_goal":false,"penalty":false,"result":null},{"team_id":"3937","type":"substitution","player_id":"4417","player_name":"Martin, Henry","related_player_id":"102966","related_player_name":"Castillo, Nicolas","minute":95,"extra_minute":null,"reason":null,"injuried":null,"own_goal":false,"penalty":false,"result":null},{"team_id":"3937","type":"yellowcard","player_id":"4411","player_name":"Vinas, Federico","related_player_id":null,"related_player_name":null,"minute":97,"extra_minute":null,"reason":null,"injuried":null,"own_goal":false,"penalty":false,"result":null},{"team_id":"3363","type":"substitution","player_id":"4395","player_name":"Pabon, Dorlan","related_player_id":"4400","related_player_name":"Gonzalez, Arturo","minute":108,"extra_minute":null,"reason":null,"injuried":null,"own_goal":false,"penalty":false,"result":null},{"team_id":"3363","type":"goal","player_id":null,"player_name":null,"related_player_id":null,"related_player_name":null,"minute":-1,"extra_minute":null,"reason":null,"injuried":null,"own_goal":false,"penalty":true,"result":"2-2"},{"team_id":"3937","type":"goal","player_id":null,"player_name":null,"related_player_id":null,"related_player_name":null,"minute":-1,"extra_minute":null,"reason":null,"injuried":null,"own_goal":false,"penalty":true,"result":"3-2"},{"team_id":"3363","type":"goal","player_id":null,"player_name":null,"related_player_id":null,"related_player_name":null,"minute":-1,"extra_minute":null,"reason":null,"injuried":null,"own_goal":false,"penalty":true,"result":"3-3"},{"team_id":"3363","type":"goal","player_id":null,"player_name":null,"related_player_id":null,"related_player_name":null,"minute":-1,"extra_minute":null,"reason":null,"injuried":null,"own_goal":false,"penalty":true,"result":"3-4"},{"team_id":"3937","type":"goal","player_id":null,"player_name":null,"related_player_id":null,"related_player_name":null,"minute":-1,"extra_minute":null,"reason":null,"injuried":null,"own_goal":false,"penalty":true,"result":"4-4"},{"team_id":"3363","type":"goal","player_id":null,"player_name":null,"related_player_id":null,"related_player_name":null,"minute":-1,"extra_minute":null,"reason":null,"injuried":null,"own_goal":false,"penalty":true,"result":"4-5"}],"meta":{"requests_left":2615,"user":"kenpetere","plan":"pack_20","pages":1,"page":1,"count":25,"total":25,"msg":null}}