{"data":[{"team_id":"3260","type":"yellowcard","player_id":"6383","player_name":"Kinda, Gadi","related_player_id":null,"related_player_name":null,"minute":9,"extra_minute":null,"reason":null,"injuried":null,"own_goal":false,"penalty":false,"result":null},{"team_id":"3260","type":"injury","player_id":"6383","player_name":"Kinda, Gadi","related_player_id":null,"related_player_name":null,"minute":21,"extra_minute":null,"reason":null,"injuried":true,"own_goal":false,"penalty":false,"result":null},{"team_id":"3260","type":"back from injury","player_id":"6383","player_name":"Kinda, Gadi","related_player_id":null,"related_player_name":null,"minute":22,"extra_minute":null,"reason":null,"injuried":false,"own_goal":false,"penalty":false,"result":null},{"team_id":"3259","type":"injury","player_id":"14542","player_name":"Dajome, Cristian","related_player_id":null,"related_player_name":null,"minute":45,"extra_minute":null,"reason":null,"injuried":true,"own_goal":false,"penalty":false,"result":null},{"team_id":"3259","type":"back from injury","player_id":"14542","player_name":"Dajome, Cristian","related_player_id":null,"related_player_name":null,"minute":45,"extra_minute":2,"reason":null,"injuried":false,"own_goal":false,"penalty":false,"result":null},{"team_id":"3259","type":"yellowcard","player_id":"17312","player_name":"Owusu, Leonard","related_player_id":null,"related_player_name":null,"minute":47,"extra_minute":null,"reason":null,"injuried":null,"own_goal":false,"penalty":false,"result":null},{"team_id":"3259","type":"yellowcard","player_id":"14554","player_name":"Gutierrez, Cristian","related_player_id":null,"related_player_name":null,"minute":59,"extra_minute":null,"reason":null,"injuried":null,"own_goal":false,"penalty":false,"result":null},{"team_id":"3260","type":"substitution","player_id":"14406","player_name":"Russell, Johnny","related_player_id":"14410","related_player_name":"Fernandes, Gerso","minute":67,"extra_minute":null,"reason":null,"injuried":null,"own_goal":false,"penalty":false,"result":null},{"team_id":"3260","type":"substitution","player_id":"14403","player_name":"Espinoza, Roger","related_player_id":"14408","related_player_name":"Busio, Gianluca","minute":67,"extra_minute":null,"reason":null,"injuried":null,"own_goal":false,"penalty":false,"result":null},{"team_id":"3259","type":"injury","player_id":null,"player_name":null,"related_player_id":null,"related_player_name":null,"minute":70,"extra_minute":null,"reason":null,"injuried":true,"own_goal":false,"penalty":false,"result":null},{"team_id":"3259","type":"substitution","player_id":"14543","player_name":"In-beom, Hwang","related_player_id":"14547","related_player_name":"Reyna, Yordy","minute":72,"extra_minute":null,"reason":null,"injuried":null,"own_goal":false,"penalty":false,"result":null},{"team_id":"3260","type":"substitution","player_id":"14404","player_name":"Shelton, Khiry","related_player_id":"14413","related_player_name":"Salloi, Daniel","minute":80,"extra_minute":null,"reason":null,"injuried":null,"own_goal":false,"penalty":false,"result":null},{"team_id":"3260","type":"goal","player_id":null,"player_name":null,"related_player_id":null,"related_player_name":null,"minute":-1,"extra_minute":null,"reason":null,"injuried":null,"own_goal":false,"penalty":true,"result":"1-0"},{"team_id":"3259","type":"goal","player_id":null,"player_name":null,"related_player_id":null,"related_player_name":null,"minute":-1,"extra_minute":null,"reason":null,"injuried":null,"own_goal":false,"penalty":true,"result":"1-1"},{"team_id":"3260","type":"goal","player_id":null,"player_name":null,"related_player_id":null,"related_player_name":null,"minute":-1,"extra_minute":null,"reason":null,"injuried":null,"own_goal":false,"penalty":true,"result":"2-1"},{"team_id":"3260","type":"goal","player_id":null,"player_name":null,"related_player_id":null,"related_player_name":null,"minute":-1,"extra_minute":null,"reason":null,"injuried":null,"own_goal":false,"penalty":true,"result":"3-1"}],"meta":{"requests_left":2089,"user":"kenpetere","plan":"pack_20","pages":1,"page":1,"count":16,"total":16,"msg":null}}